aiosearchads/__init__.py
aiosearchads/__version__.py
aiosearchads-0.0.3.dist-info/LICENSE
aiosearchads-0.0.3.dist-info/METADATA
aiosearchads-0.0.3.dist-info/WHEEL
aiosearchads-0.0.3.dist-info/top_level.txt
aiosearchads-0.0.3.dist-info/RECORD
