Metadata-Version: 2.1
Name: aiosearchads
Version: 0.0.3
Summary: Asynchronous apple searchads framework for asyncio and Python
Home-page: https://github.com/linzhiming0826/aiosearchads
Author: TuoX
Author-email: 120549827@qq.com
License: MIT
Platform: any
Classifier: Programming Language :: Python :: 3.6
Classifier: Programming Language :: Python :: 3.7
Classifier: License :: OSI Approved :: MIT License
License-File: LICENSE
Requires-Dist: aiohttp (>=3.6.2)
Requires-Dist: pyjwt (>=1.7.1)
